gds_lmcache.libs/libcufile-b57e4bac.so.0
gds_lmcache/__init__.py
gds_lmcache/gds_lmcache.cpython-312-x86_64-linux-gnu.so
gds_lmcache_rs-0.2.2.dist-info/METADATA
gds_lmcache_rs-0.2.2.dist-info/WHEEL
gds_lmcache_rs-0.2.2.dist-info/licenses/LICENSE
gds_lmcache_rs-0.2.2.dist-info/RECORD
