Metadata-Version: 2.4
Name: gds-lmcache-rs
Version: 0.2.2
Classifier: Programming Language :: Python
Classifier: Programming Language :: Rust
Classifier: License :: OSI Approved :: MIT License
Classifier: Operating System :: OS Independent
License-File: LICENSE
Summary: Rust-based GDS Backend for LMCache
Author-email: Serapheim Dimitropoulos <serapheim.dimitropoulos@weka.io>
Requires-Python: >=3.10
